snake_logic.v
`timescale 1ns/1ps

module snake_logic #(
    parameter BOARD_WIDTH = 20,
    parameter BOARD_HEIGHT = 20,
    parameter ADDR_WIDTH = 5 
) (
    input wire clk,
    input wire reset,

    input wire [1:0] direction,
    input wire [ADDR_WIDTH-1:0] head_x,
    input wire [ADDR_WIDTH-1:0] head_y,

    output reg [ADDR_WIDTH-1:0] next_head_x,
    output reg [ADDR_WIDTH-1:0] next_head_y
);

    reg [ADDR_WIDTH:0] new_x, new_y; 
    
    localparam DIR_NORTH = 2'b00;
    localparam DIR_EAST  = 2'b01;
    localparam DIR_SOUTH = 2'b10;
    localparam DIR_WEST  = 2'b11;

    always @(*) begin
        case (direction)
            DIR_NORTH: begin
                new_x = {1'b0, head_x};
                new_y = {1'b0, head_y} - 6'd1;
            end
            DIR_EAST: begin
                new_x = {1'b0, head_x} + 6'd1;
                new_y = {1'b0, head_y};
            end
            DIR_SOUTH: begin
                new_x = {1'b0, head_x};
                new_y = {1'b0, head_y} + 6'd1;
            end
            DIR_WEST: begin
                new_x = {1'b0, head_x} - 6'd1;
                new_y = {1'b0, head_y};
            end
            default: begin
                new_x = {1'b0, head_x};
                new_y = {1'b0, head_y};
            end
        endcase
    end

    always @(posedge clk or posedge reset) begin
        if (reset) begin
            next_head_x <= BOARD_WIDTH / 2;
            next_head_y <= BOARD_HEIGHT / 2;
        end else begin
            if (new_x == BOARD_WIDTH) begin
                next_head_x <= 0;
            end else if (new_x == {ADDR_WIDTH+1{1'b1}}) begin 
                next_head_x <= BOARD_WIDTH - 1; // 19
            end else begin
                next_head_x <= new_x[ADDR_WIDTH-1:0]; 
            end

            if (new_y == BOARD_HEIGHT) begin
                next_head_y <= 0;
            end else if (new_y == {ADDR_WIDTH+1{1'b1}}) begin 
                next_head_y <= BOARD_HEIGHT - 1; // 19
            end else begin
                next_head_y <= new_y[ADDR_WIDTH-1:0];
            end
        end
    end

endmodule

Verilog/snake_tb.v
`timescale 1ns/1ps

module snake_tb;

    parameter BOARD_WIDTH = 20;
    parameter BOARD_HEIGHT = 20;
    parameter ADDR_WIDTH = 5; 

    reg clk;
    reg reset;
    reg test_enable; 
    reg [1:0] direction;
    reg [ADDR_WIDTH-1:0] head_x;
    reg [ADDR_WIDTH-1:0] head_y;

    wire [ADDR_WIDTH-1:0] next_head_x;
    wire [ADDR_WIDTH-1:0] next_head_y;

    snake_logic #(
        .BOARD_WIDTH(BOARD_WIDTH),
        .BOARD_HEIGHT(BOARD_HEIGHT),
        .ADDR_WIDTH(ADDR_WIDTH)
    ) UUT (
        .clk(clk),
        .reset(reset),
        .direction(direction),
        .head_x(head_x),
        .head_y(head_y),
        .next_head_x(next_head_x),
        .next_head_y(next_head_y)
    );

    initial begin
        clk = 0;
        forever #10 clk = ~clk;
    end


    initial begin
        $dumpfile("snake_waves.vcd");
        $dumpvars(0, snake_tb);
        $display("VCD file snake_waves.vcd generated.");
    end

    always @(posedge clk) begin
        if (!reset && test_enable) begin

            head_x <= next_head_x;
            head_y <= next_head_y;
        end
    end

    initial begin

        reset = 1;
        test_enable = 0;
        direction = 2'b00; 
        head_x = 10;
        head_y = 10;
        
        #20 reset = 0; 

        @(posedge clk);
        
        $display("--- Test 1: Moving East (No wrap, 20 cycles) ---");
        test_enable = 1; 
        direction = 2'b01; 
        #400; 

        $display("--- Test 2: Wrap-around East (X=19 -> 0) ---");
        test_enable = 0; 
        @(posedge clk); 
        
        head_x = 19;
        head_y = 10;
        
        test_enable = 1; 
        direction = 2'b01; 
        #40;

        $display("--- Test 3: Wrap-around North (Y=0 -> 19) ---");
        test_enable = 0; 
        @(posedge clk); 

        head_x = 10;
        head_y = 0;
        
        test_enable = 1; 
        direction = 2'b00; 
        #40; 

        $display("Test sequence complete.");
        test_enable = 0;
        #10 $finish;
    end

endmodule

snake_waves.vcd
$date
	Thu Dec 04 18:43:39 2025
$end
$version
	Icarus Verilog
$end
$timescale
	1ps
$end
$scope module snake_tb $end
$var wire 5 ! next_head_y [4:0] $end
$var wire 5 " next_head_x [4:0] $end
$var parameter 32 # ADDR_WIDTH $end
$var parameter 32 $ BOARD_HEIGHT $end
$var parameter 32 % BOARD_WIDTH $end
$var reg 1 & clk $end
$var reg 2 ' direction [1:0] $end
$var reg 5 ( head_x [4:0] $end
$var reg 5 ) head_y [4:0] $end
$var reg 1 * reset $end
$var reg 1 + test_enable $end
$scope module UUT $end
$var wire 1 & clk $end
$var wire 2 , direction [1:0] $end
$var wire 5 - head_x [4:0] $end
$var wire 5 . head_y [4:0] $end
$var wire 1 * reset $end
$var parameter 32 / ADDR_WIDTH $end
$var parameter 32 0 BOARD_HEIGHT $end
$var parameter 32 1 BOARD_WIDTH $end
$var parameter 2 2 DIR_EAST $end
$var parameter 2 3 DIR_NORTH $end
$var parameter 2 4 DIR_SOUTH $end
$var parameter 2 5 DIR_WEST $end
$var reg 6 6 new_x [5:0] $end
$var reg 6 7 new_y [5:0] $end
$var reg 5 8 next_head_x [4:0] $end
$var reg 5 9 next_head_y [4:0] $end
$upscope $end
$upscope $end
$enddefinitions $end
$comment Show the parameter values. $end
$dumpall
b11 5
b10 4
b0 3
b1 2
b10100 1
b10100 0
b101 /
b10100 %
b10100 $
b101 #
$end
#0
$dumpvars
b1010 9
b1010 8
b1001 7
b1010 6
b1010 .
b1010 -
b0 ,
0+
1*
b1010 )
b1010 (
b0 '
0&
b1010 "
b1010 !
$end
#10000
1&
#20000
0&
0*
#30000
b1001 !
b1001 9
b1010 7
b1011 6
b1 '
b1 ,
1+
1&
#40000
0&
#50000
b1001 7
b1010 !
b1010 9
b1011 "
b1011 8
b1001 )
b1001 .
1&
#60000
0&
#70000
b1010 7
b1100 6
b1001 !
b1001 9
b1010 )
b1010 .
b1011 (
b1011 -
1&
#80000
0&
#90000
b1001 7
b1010 !
b1010 9
b1100 "
b1100 8
b1001 )
b1001 .
1&
#100000
0&
#110000
b1010 7
b1101 6
b1001 !
b1001 9
b1010 )
b1010 .
b1100 (
b1100 -
1&
#120000
0&
#130000
b1001 7
b1010 !
b1010 9
b1101 "
b1101 8
b1001 )
b1001 .
1&
#140000
0&
#150000
b1010 7
b1110 6
b1001 !
b1001 9
b1010 )
b1010 .
b1101 (
b1101 -
1&
#160000
0&
#170000
b1001 7
b1010 !
b1010 9
b1110 "
b1110 8
b1001 )
b1001 .
1&
#180000
0&
#190000
b1010 7
b1111 6
b1001 !
b1001 9
b1010 )
b1010 .
b1110 (
b1110 -
1&
#200000
0&
#210000
b1001 7
b1010 !
b1010 9
b1111 "
b1111 8
b1001 )
b1001 .
1&
#220000
0&
#230000
b1010 7
b10000 6
b1001 !
b1001 9
b1010 )
b1010 .
b1111 (
b1111 -
1&
#240000
0&
#250000
b1001 7
b1010 !
b1010 9
b10000 "
b10000 8
b1001 )
b1001 .
1&
#260000
0&
#270000
b1010 7
b10001 6
b1001 !
b1001 9
b1010 )
b1010 .
b10000 (
b10000 -
1&
#280000
0&
#290000
b1001 7
b1010 !
b1010 9
b10001 "
b10001 8
b1001 )
b1001 .
1&
#300000
0&
#310000
b1010 7
b10010 6
b1001 !
b1001 9
b1010 )
b1010 .
b10001 (
b10001 -
1&
#320000
0&
#330000
b1001 7
b1010 !
b1010 9
b10010 "
b10010 8
b1001 )
b1001 .
1&
#340000
0&
#350000
b1010 7
b10011 6
b1001 !
b1001 9
b1010 )
b1010 .
b10010 (
b10010 -
1&
#360000
0&
#370000
b1001 7
b1010 !
b1010 9
b10011 "
b10011 8
b1001 )
b1001 .
1&
#380000
0&
#390000
b1010 7
b10100 6
b1001 !
b1001 9
b1010 )
b1010 .
b10011 (
b10011 -
1&
#400000
0&
#410000
b1001 7
b1010 !
b1010 9
b0 "
b0 8
b1001 )
b1001 .
1&
#420000
0&
#430000
b1 6
b1001 !
b1001 9
b0 (
b0 -
b1010 7
b1010 )
b1010 .
1&
1+
#440000
0&
#450000
b1001 7
b1010 !
b1010 9
b1 "
b1 8
b1001 )
b1001 .
1&
#460000
0&
#470000
b1001 !
b1001 9
b1001 7
b1 6
b0 '
b0 ,
b1010 )
b1010 .
b1 (
b1 -
1&
1+
#480000
0&
#490000
b1000 7
b1001 )
b1001 .
1&
#500000
0&
#510000
b1000 !
b1000 9
1&
0+
